robot/stopwatch/StopwatchListener.py
robot/stopwatch/__init__.py
robotframework_stopwatch-0.2.10.dist-info/LICENSE
robotframework_stopwatch-0.2.10.dist-info/METADATA
robotframework_stopwatch-0.2.10.dist-info/WHEEL
robotframework_stopwatch-0.2.10.dist-info/top_level.txt
robotframework_stopwatch-0.2.10.dist-info/RECORD
