Metadata-Version: 2.1
Name: robotframework-stopwatch
Version: 0.2.10
Summary: Evaluate test case execution against its statistical average run time & user-configured timedelta.
Author-email: extraorange <extraorangeio@pm.me>
License: GPL-3.0-only
Project-URL: Homepage, https://github.com/extraorange/robotframework-stopwatch
Project-URL: Documentation, https://github.com/yourusername/robotframework-stopwatch#readme
Keywords: robotframework,listener,robot framework,automation,performance testing
Classifier: Development Status :: 4 - Beta
Classifier: Framework :: Robot Framework :: Library
Classifier: Intended Audience :: Developers
Classifier: License :: OSI Approved :: GNU General Public License v3 (GPLv3)
Classifier: Operating System :: OS Independent
Classifier: Programming Language :: Python :: 3
Classifier: Topic :: Software Development :: Testing :: Acceptance
Classifier: Topic :: Software Development :: Testing :: BDD
Classifier: Topic :: Software Development :: Testing
Classifier: Operating System :: OS Independent
Requires-Python: >=3.8
License-File: LICENSE
Requires-Dist: robotframework >=6.1.1
